<?xml version="1.0" ?>
<timetable station="Bad Kohlgrub Kurhaus" eva="8000717">
	


	<s id="-3490715095428484089-2508040553-5" eva="8000717">
		
    
		<ar ct="2508040608" l="63"/>
		
    
		<dp ct="2508040609" l="63"/>
		

	</s>
	



	<s id="194765326825394615-2508040558-6" eva="8000717">
		
    
		<ar ct="2508040619" l="63"/>
		
    
		<dp ct="2508040620" l="63"/>
		

	</s>
	



	<s id="-7771116484878088185-2508040505-6" eva="8000717">
		
    
		<ar ct="2508040526" l="63"/>
		
    
		<dp ct="2508040526" l="63"/>
		

	</s>
	



	<s id="3583579412380481861-2508040500-5" eva="8000717">
		
    
		<ar ct="2508040517" l="63"/>
		
    
		<dp ct="2508040515" l="63"/>
		

	</s>
	



	<s id="7532104411908698692-2508032334-6" eva="8000717">
		
    
		<ar ct="2508032356" l="63"/>
		
    
		<dp ct="2508032357" l="63"/>
		

	</s>
	



	<s id="814528122550672379-2508032329-5" eva="8000717">
		
    
		<ar ct="2508032344" l="63"/>
		
    
		<dp ct="2508032344" l="63"/>
		

	</s>
	



	<s id="-8839148860473451277-2508032242-6" eva="8000717">
		
    
		<ar ct="2508032302" l="63"/>
		
    
		<dp ct="2508032303" l="63"/>
		

	</s>
	



	<s id="-602430826060204979-2508032238-5" eva="8000717">
		
    
		<ar ct="2508032253" l="63"/>
		
    
		<dp ct="2508032253" l="63"/>
		

	</s>
	


</timetable>
