<?xml version="1.0" ?>
<timetable station="Blindheim" eva="8001028">
	


	<s id="-4100104679560117039-2507211047-10" eva="8001028">
		
    
		<ar ct="2507211137" l="RB15">
			
        
			<m id="r21335721" t="d" c="43" ts="2507211121" ts-tts="25-07-21 11:21:31.668"/>
			
    
		</ar>
		
    
		<dp ct="2507211138" l="RB15">
			
        
			<m id="r21335721" t="d" c="43" ts="2507211121" ts-tts="25-07-21 11:21:31.668"/>
			
    
		</dp>
		

	</s>
	



	<s id="3504493641036294166-2507211011-13" eva="8001028">
		
    
		<ar ct="2507211114" l="RB15"/>
		
    
		<dp ct="2507211115" l="RB15"/>
		

	</s>
	



	<s id="-8410925947695584863-2507211511-13" eva="8001028">
		
    
		<ar ct="2507211627" l="RB15"/>
		
    
		<dp ct="2507211627" l="RB15"/>
		

	</s>
	



	<s id="2868854051011682435-2507211447-10" eva="8001028">
		
    
		<ar ct="2507211532" l="RB15"/>
		
    
		<dp ct="2507211533" l="RB15"/>
		

	</s>
	



	<s id="6988273470950354533-2507210947-10" eva="8001028">
		
    
		<ar ct="2507211039" l="RB15"/>
		
    
		<dp ct="2507211040" l="RB15"/>
		

	</s>
	



	<s id="-6090478317840431028-2507210905-13" eva="8001028">
		
    
		<ar ct="2507211028" l="RB15">
			
        
			<m id="r21329413" t="f" c="0" ts="2507210856" ts-tts="25-07-21 08:57:04.424"/>
			
        
			<m id="r21332988" t="d" c="21" ts="2507211023" ts-tts="25-07-21 10:23:16.819"/>
			
    
		</ar>
		
    
		<dp ct="2507211028" l="RB15">
			
        
			<m id="r21329413" t="f" c="0" ts="2507210856" ts-tts="25-07-21 08:57:04.424"/>
			
        
			<m id="r21332988" t="d" c="21" ts="2507211023" ts-tts="25-07-21 10:23:16.819"/>
			
    
		</dp>
		

	</s>
	



	<s id="-6062677638181210291-2507211411-13" eva="8001028">
		
    
		<ar ct="2507211513" l="RB15"/>
		
    
		<dp ct="2507211513" l="RB15"/>
		

	</s>
	



	<s id="-5023902995770073206-2507211347-10" eva="8001028">
		
    
		<ar ct="2507211435" l="RB15"/>
		
    
		<dp ct="2507211436" l="RB15"/>
		

	</s>
	



	<s id="3029995909685443034-2507210847-10" eva="8001028">
		
    
		<ar cpth="Ulm Hbf|Neu-Ulm|Nersingen|Leipheim|Günzburg|Gundelfingen(Bay)|Lauingen|Dillingen(Donau)|Höchstädt(Donau)" ct="2507210935" l="RB15">
			
        
			<m id="r21330601" t="d" c="43" ts="2507210928" ts-tts="25-07-21 09:28:16.641"/>
			
    
		</ar>
		
    
		<dp cpth="Schwenningen(Bay)|Tapfheim|Donauwörth|Genderkingen|Rain|Burgheim|Straß-Moos|Unterhausen(Bay)|Neuburg(Donau)|Rohrenfeld|Weichering|Ingolstadt Hbf" ct="2507210935" l="RB15">
			
        
			<m id="r21330601" t="d" c="43" ts="2507210928" ts-tts="25-07-21 09:28:16.641"/>
			
    
		</dp>
		

	</s>
	



	<s id="-5881319162620217750-2507210810-13" eva="8001028">
		
    
		<ar ct="2507210917" l="RB15">
			
        
			<m id="r21329341" t="d" c="43" ts="2507210855" ts-tts="25-07-21 08:55:13.286"/>
			
    
		</ar>
		
    
		<dp ct="2507210917" l="RB15">
			
        
			<m id="r21329341" t="d" c="43" ts="2507210855" ts-tts="25-07-21 08:55:13.286"/>
			
    
		</dp>
		

	</s>
	



	<s id="6195597648115269974-2507211311-13" eva="8001028">
		
    
		<ar ct="2507211427" l="RB15"/>
		
    
		<dp ct="2507211427" l="RB15"/>
		

	</s>
	



	<s id="-1170527325601688725-2507210701-12" eva="8001028">
		
    
		<ar cpth="Weichering|Ingolstadt Hbf|Rohrenfeld|Neuburg(Donau)|Unterhausen(Bay)|Straß-Moos|Burgheim|Rain|Genderkingen|Donauwörth|Schwenningen(Bay)" ct="2507210831" l="RB15">
			
        
			<m id="r21319693" t="d" c="47" ts="2507210434" ts-tts="25-07-21 04:34:36.564"/>
			
        
			<m id="r21328116" t="d" c="43" ts="2507210826" ts-tts="25-07-21 08:26:19.279"/>
			
        
			<m id="r21329648" t="d" c="45" ts="2507210902" ts-tts="25-07-21 09:02:52.732"/>
			
    
		</ar>
		
    
		<dp cpth="Höchstädt(Donau)|Dillingen(Donau)|Lauingen|Gundelfingen(Bay)|Günzburg|Leipheim|Nersingen|Neu-Ulm|Ulm Hbf" ct="2507210832" l="RB15">
			
        
			<m id="r21319693" t="d" c="47" ts="2507210434" ts-tts="25-07-21 04:34:36.564"/>
			
        
			<m id="r21328116" t="d" c="43" ts="2507210826" ts-tts="25-07-21 08:26:19.279"/>
			
        
			<m id="r21329648" t="d" c="45" ts="2507210902" ts-tts="25-07-21 09:02:52.732"/>
			
    
		</dp>
		

	</s>
	



	<s id="-1297617144383973978-2507211250-6" eva="8001028">
		
    
		<ar ct="2507211316" l="RB15"/>
		
    
		<dp ct="2507211317" l="RB15"/>
		

	</s>
	



	<s id="-18413819651246613-2507211247-10" eva="8001028">
		
    
		<ar ct="2507211337" l="RB15"/>
		
    
		<dp ct="2507211338" l="RB15"/>
		

	</s>
	



	<s id="-8599674944749570300-2507210747-10" eva="8001028">
		
    
		<ar ct="2507210840" l="RB15"/>
		
    
		<dp ct="2507210840" l="RB15"/>
		

	</s>
	



	<s id="-3723507688118590751-2507210740-6" eva="8001028">
		
    
		<ar ct="2507210812" l="RB15"/>
		
    
		<dp ct="2507210812" l="RB15"/>
		

	</s>
	



	<s id="4550917788441503831-2507211211-13" eva="8001028">
		
    
		<ar ct="2507211313" l="RB15"/>
		
    
		<dp ct="2507211318" l="RB15"/>
		

	</s>
	



	<s id="-8948241013011651976-2507211147-10" eva="8001028">
		
    
		<ar ct="2507211235" l="RB15"/>
		
    
		<dp ct="2507211236" l="RB15"/>
		

	</s>
	



	<s id="3418799343998839220-2507210627-13" eva="8001028">
		
    
		<ar ct="2507210745" l="RB15"/>
		
    
		<dp ct="2507210746" l="RB15"/>
		

	</s>
	



	<s id="2932282650870546949-2507212311-13" eva="8001028">
		
    
		<ar ct="2507220011" l="RB15"/>
		
    
		<dp ct="2507220012" l="RB15"/>
		

	</s>
	



	<s id="-2734331739070172878-2507210626-10" eva="8001028">
		
    
		<ar ct="2507210711" l="RB15"/>
		
    
		<dp ct="2507210714" l="RB15"/>
		

	</s>
	



	<s id="796237016836454287-2507210556-13" eva="8001028">
		
    
		<ar ct="2507210714" l="RB15"/>
		
    
		<dp ct="2507210715" l="RB15"/>
		

	</s>
	



	<s id="-1596679165196866882-2507211111-13" eva="8001028">
		
    
		<ar ct="2507211227" l="RB15"/>
		
    
		<dp ct="2507211227" l="RB15"/>
		

	</s>
	



	<s id="-6244698324564251566-2507210552-10" eva="8001028">
		
    
		<ar ct="2507210650" l="RB15"/>
		
    
		<dp ct="2507210650" l="RB15"/>
		

	</s>
	



	<s id="72226929427361436-2507210623-3" eva="8001028">
		
    
		<ar ct="2507210640" l="RB15"/>
		
    
		<dp ct="2507210641" l="RB15"/>
		

	</s>
	



	<s id="8912048394049036116-2507210531-10" eva="8001028">
		
    
		<ar ct="2507210630" l="RB15">
			
        
			<m id="r21322350" t="d" c="43" ts="2507210622" ts-tts="25-07-21 06:22:09.851"/>
			
    
		</ar>
		
    
		<dp ct="2507210630" l="RB15">
			
        
			<m id="r21322350" t="d" c="43" ts="2507210622" ts-tts="25-07-21 06:22:09.851"/>
			
    
		</dp>
		

	</s>
	



	<s id="6223595504979038932-2507210505-13" eva="8001028">
		
    
		<ar ct="2507210611" l="RB15"/>
		
    
		<dp ct="2507210612" l="RB15"/>
		

	</s>
	



	<s id="9215471812401632440-2507210453-10" eva="8001028">
		
    
		<ar ct="2507210538" l="RB15"/>
		
    
		<dp ct="2507210538" l="RB15"/>
		

	</s>
	



	<s id="2572569814100323534-2507210447-4" eva="8001028">
		
    
		<ar ct="2507210459" l="RB15"/>
		
    
		<dp ct="2507210500" l="RB15"/>
		

	</s>
	


</timetable>
