<?xml version="1.0" ?>
<timetable station="Westerham" eva="8006366">
	


	<s id="-2759690155523500432-2505291740-11" eva="8006366">
		
    
		<ar ct="2505291810" l="RB58">
			
        
			<m id="r18467439" t="d" c="99" ts="2505291744" ts-tts="25-05-29 17:44:28.196"/>
			
    
		</ar>
		
    
		<dp ct="2505291811" l="RB58">
			
        
			<m id="r18467439" t="d" c="99" ts="2505291744" ts-tts="25-05-29 17:44:28.196"/>
			
    
		</dp>
		

	</s>
	



	<s id="-9134013784809639849-2505291737-3" eva="8006366">
		
    
		<ar ct="2505291750" l="RB58"/>
		
    
		<dp ct="2505291752" l="RB58"/>
		

	</s>
	



	<s id="-988657340425219817-2505292144-2" eva="8006366">
		
    
		<ar ct="2505292150" l="RB58"/>
		
    
		<dp ct="2505292151" l="RB58"/>
		

	</s>
	



	<s id="8433647612880255595-2505292140-11" eva="8006366">
		
    
		<ar ct="2505292207" l="RB58"/>
		
    
		<dp ct="2505292208" l="RB58"/>
		

	</s>
	



	<s id="-875217255437925122-2505291640-11" eva="8006366">
		
    
		<ar ct="2505291708" l="RB58"/>
		
    
		<dp ct="2505291709" l="RB58"/>
		

	</s>
	



	<s id="-6336870831846274887-2505291637-3" eva="8006366">
		
    
		<ar ct="2505291651" l="RB58"/>
		
    
		<dp ct="2505291652" l="RB58"/>
		

	</s>
	



	<s id="8830939802424709464-2505292040-11" eva="8006366">
		
    
		<ar ct="2505292107" l="RB58"/>
		
    
		<dp ct="2505292108" l="RB58"/>
		

	</s>
	



	<s id="-1211240558580121676-2505292037-3" eva="8006366">
		
    
		<ar ct="2505292050" l="RB58"/>
		
    
		<dp ct="2505292051" l="RB58"/>
		

	</s>
	



	<s id="7110998769838413001-2505291540-11" eva="8006366">
		
    
		<ar ct="2505291608" l="RB58"/>
		
    
		<dp ct="2505291609" l="RB58"/>
		

	</s>
	



	<s id="4258136949840027066-2505291537-3" eva="8006366">
		
    
		<ar ct="2505291550" l="RB58"/>
		
    
		<dp ct="2505291550" l="RB58"/>
		

	</s>
	



	<s id="6266896497198133427-2505291940-11" eva="8006366">
		
    
		<ar ct="2505292006" l="RB58"/>
		
    
		<dp ct="2505292007" l="RB58"/>
		

	</s>
	



	<s id="2368864935089921386-2505291937-3" eva="8006366">
		
    
		<ar ct="2505291950" l="RB58"/>
		
    
		<dp ct="2505291950" l="RB58"/>
		

	</s>
	



	<s id="6293422997956792268-2505291440-11" eva="8006366">
		
    
		<ar ct="2505291509" l="RB58"/>
		
    
		<dp ct="2505291510" l="RB58"/>
		

	</s>
	



	<s id="-937059037036675828-2505291437-3" eva="8006366">
		
    
		<ar ct="2505291451" l="RB58"/>
		
    
		<dp ct="2505291452" l="RB58"/>
		

	</s>
	



	<s id="-1176454295799552-2505291840-11" eva="8006366">
		
    
		<ar ct="2505291906" l="RB58"/>
		
    
		<dp ct="2505291907" l="RB58"/>
		

	</s>
	



	<s id="8726505300763402746-2505291837-3" eva="8006366">
		
    
		<ar ct="2505291850" l="RB58"/>
		
    
		<dp ct="2505291850" l="RB58"/>
		

	</s>
	



	<s id="4443420966560724956-2505291340-11" eva="8006366">
		
    
		<ar ct="2505291409" l="RB58"/>
		
    
		<dp ct="2505291411" l="RB58"/>
		

	</s>
	



	<s id="-2123363613713652691-2505291337-3" eva="8006366">
		
    
		<ar ct="2505291350" l="RB58"/>
		
    
		<dp ct="2505291351" l="RB58"/>
		

	</s>
	



	<s id="225219423366859174-2505291240-11" eva="8006366">
		
    
		<ar ct="2505291308" l="RB58"/>
		
    
		<dp ct="2505291309" l="RB58"/>
		

	</s>
	



	<s id="7001697263208975960-2505291237-3" eva="8006366">
		
    
		<ar ct="2505291251" l="RB58"/>
		
    
		<dp ct="2505291252" l="RB58"/>
		

	</s>
	



	<s id="8988901053646305818-2505291140-11" eva="8006366">
		
    
		<ar ct="2505291210" l="RB58">
			
        
			<m id="r18453629" t="d" c="43" ts="2505291203" ts-tts="25-05-29 12:03:18.338"/>
			
    
		</ar>
		
    
		<dp ct="2505291211" l="RB58">
			
        
			<m id="r18453629" t="d" c="43" ts="2505291203" ts-tts="25-05-29 12:03:18.338"/>
			
    
		</dp>
		

	</s>
	



	<s id="-1934286470876742075-2505291137-3" eva="8006366">
		
    
		<ar ct="2505291150" l="RB58"/>
		
    
		<dp ct="2505291151" l="RB58"/>
		

	</s>
	



	<s id="4062451382511416210-2505291040-11" eva="8006366">
		
    
		<ar ct="2505291108" l="RB58"/>
		
    
		<dp ct="2505291109" l="RB58"/>
		

	</s>
	



	<s id="6067240894965152785-2505291037-3" eva="8006366">
		
    
		<ar ct="2505291051" l="RB58"/>
		
    
		<dp ct="2505291051" l="RB58"/>
		

	</s>
	


</timetable>
