<?xml version="1.0" ?>
<timetable station="Sonthofen">
	<s id="9030129867999440752-2505261302-7">
		<tl f="N" t="p" o="8007D4" c="RE" n="56063"/>
		<ar pt="2505261400" pp="3" l="75" ppth="Memmingen|Dietmannsried|Kempten(Allgäu)Hbf|Martinszell(Allgäu)|Immenstadt|Blaichach(Allgäu)"/>
		<dp pt="2505261400" pp="3" l="75" ppth="Altstädten(Allgäu)|Fischen|Langenwang(Schwab)|Oberstdorf"/>
	</s>
	<s id="-6142879137720402396-2505261334-5">
		<tl f="N" t="p" o="8007D4" c="RE" n="56082"/>
		<ar pt="2505261359" pp="1" l="75" ppth="Oberstdorf|Langenwang(Schwab)|Fischen|Altstädten(Allgäu)"/>
		<dp pt="2505261401" pp="1" l="75" ppth="Blaichach(Allgäu)|Immenstadt|Martinszell(Allgäu)|Kempten(Allgäu)Hbf|Dietmannsried|Memmingen"/>
	</s>
	<s id="2628781339817811946-2505261434-5">
		<tl f="N" t="p" o="8007D4" c="RE" n="56070"/>
		<ar pt="2505261459" pp="1" l="75" ppth="Oberstdorf|Langenwang(Schwab)|Fischen|Altstädten(Allgäu)"/>
		<dp pt="2505261501" pp="1" l="75" ppth="Blaichach(Allgäu)|Immenstadt|Martinszell(Allgäu)|Kempten(Allgäu)Hbf|Kempten(Allgäu)Ost|Dietmannsried|Bad Grönenbach|Memmingen"/>
	</s>
	<s id="-1027776970131509053-2505261241-7">
		<tl f="N" t="p" o="8007D5" c="RE" n="3390"/>
		<ar pt="2505261420" pp="1" l="17" ppth="Augsburg Hbf|Buchloe|Kaufbeuren|Kempten(Allgäu)Hbf|Immenstadt|Blaichach(Allgäu)"/>
		<dp pt="2505261421" pp="1" l="17" ppth="Fischen|Oberstdorf"/>
	</s>
	<s id="-3558280718584643643-2505261423-5">
		<tl f="N" t="p" o="8007D5" c="RE" n="7885"/>
		<ar pt="2505261442" pp="1" l="76" ppth="Oberstdorf|Langenwang(Schwab)|Fischen|Altstädten(Allgäu)"/>
		<dp pt="2505261442" pp="1" l="76" ppth="Blaichach(Allgäu)|Immenstadt|Kempten(Allgäu)Hbf|Kaufbeuren|Buchloe|Kaufering|Geltendorf|München-Pasing|München Hbf Gl.27-36"/>
	</s>
</timetable>
