<?xml version="1.0" ?>
<timetable station="Kronach" eva="8003446">
	


	<s id="3810604004206703964-2507272138-19" eva="8003446">
		
    
		<m id="r2197542" t="h" from="2507150000" to="2508041000" cat="Bauarbeiten" ts="2507212300" ts-tts="25-07-26 23:16:03.951" pr="2"/>
		
    
		<ar ct="2507272324" l="14"/>
		
    
		<dp ct="2507272325" l="14"/>
		

	</s>
	



	<s id="3675320541711482357-2507281505-15" eva="8003446">
		
    
		<m id="r2444956" t="h" from="2506240000" to="2507302359" cat="Information" ts="2506241537" ts-tts="25-07-27 23:16:04.392" pr="2"/>
		

	</s>
	



	<s id="-2596384342536523823-2507280749-9" eva="8003446">
		
    
		<m id="r2444956" t="h" from="2506240000" to="2507302359" cat="Information" ts="2506241537" ts-tts="25-07-27 23:16:04.392" pr="2"/>
		

	</s>
	



	<s id="5532038320047824464-2507281305-14" eva="8003446">
		
    
		<m id="r2444956" t="h" from="2506240000" to="2507302359" cat="Information" ts="2506241537" ts-tts="25-07-27 23:16:04.392" pr="2"/>
		

	</s>
	



	<s id="3302578414229695927-2507280949-9" eva="8003446">
		
    
		<m id="r2444956" t="h" from="2506240000" to="2507302359" cat="Information" ts="2506241537" ts-tts="25-07-27 23:16:04.392" pr="2"/>
		

	</s>
	



	<s id="-113756971786229411-2507280905-14" eva="8003446">
		
    
		<m id="r2444956" t="h" from="2506240000" to="2507302359" cat="Information" ts="2506241537" ts-tts="25-07-27 23:16:04.392" pr="2"/>
		

	</s>
	



	<s id="-3892470588894151283-2507281349-9" eva="8003446">
		
    
		<m id="r2444956" t="h" from="2506240000" to="2507302359" cat="Information" ts="2506241537" ts-tts="25-07-27 23:16:04.392" pr="2"/>
		

	</s>
	



	<s id="3538447596943178203-2507280706-16" eva="8003446">
		
    
		<m id="r2444956" t="h" from="2506240000" to="2507302359" cat="Information" ts="2506241537" ts-tts="25-07-27 23:16:04.392" pr="2"/>
		

	</s>
	



	<s id="2044823728383562621-2507281549-9" eva="8003446">
		
    
		<m id="r2444956" t="h" from="2506240000" to="2507302359" cat="Information" ts="2506241537" ts-tts="25-07-27 23:16:04.392" pr="2"/>
		

	</s>
	



	<s id="-2150810590113832298-2507280657-12" eva="8003446">
		
    
		<m id="r2430602" t="h" from="2507120000" to="2507310100" cat="Bauarbeiten" ts="2507112306" ts-tts="25-07-27 23:16:04.221" pr="2"/>
		

	</s>
	



	<s id="-6459206617103634837-2507281538-13" eva="8003446">
		
    
		<m id="r2197542" t="h" from="2507150000" to="2508041000" cat="Bauarbeiten" ts="2507212300" ts-tts="25-07-27 23:16:04.178" pr="2"/>
		
    
		<ar l="14">
			
        
			<m id="r21691528" t="f" c="0" ts="2507272100" ts-tts="25-07-27 21:00:29.940"/>
			
    
		</ar>
		
    
		<dp l="14">
			
        
			<m id="r21691528" t="f" c="0" ts="2507272100" ts-tts="25-07-27 21:00:29.940"/>
			
    
		</dp>
		

	</s>
	



	<s id="2975085315850444113-2507281338-13" eva="8003446">
		
    
		<m id="r2197542" t="h" from="2507150000" to="2508041000" cat="Bauarbeiten" ts="2507212300" ts-tts="25-07-27 23:16:04.177" pr="2"/>
		

	</s>
	



	<s id="5781938573076983826-2507281138-13" eva="8003446">
		
    
		<m id="r2197542" t="h" from="2507150000" to="2508041000" cat="Bauarbeiten" ts="2507212300" ts-tts="25-07-27 23:16:04.177" pr="2"/>
		

	</s>
	



	<s id="-3402290241958999151-2507280938-13" eva="8003446">
		
    
		<m id="r2197542" t="h" from="2507150000" to="2508041000" cat="Bauarbeiten" ts="2507212300" ts-tts="25-07-27 23:16:04.177" pr="2"/>
		

	</s>
	



	<s id="-7698587961565818966-2507280738-13" eva="8003446">
		
    
		<m id="r2197542" t="h" from="2507150000" to="2508041000" cat="Bauarbeiten" ts="2507212300" ts-tts="25-07-27 23:16:04.177" pr="2"/>
		

	</s>
	



	<s id="1478557104463101738-2507281440-11" eva="8003446">
		
    
		<m id="r2197542" t="h" from="2507150000" to="2508041000" cat="Bauarbeiten" ts="2507212300" ts-tts="25-07-27 23:16:04.177" pr="2"/>
		

	</s>
	



	<s id="7820453276416715184-2507281238-14" eva="8003446">
		
    
		<m id="r2197542" t="h" from="2507150000" to="2508041000" cat="Bauarbeiten" ts="2507212300" ts-tts="25-07-27 23:16:04.177" pr="2"/>
		

	</s>
	



	<s id="7278607554574787983-2507281040-11" eva="8003446">
		
    
		<m id="r2197542" t="h" from="2507150000" to="2508041000" cat="Bauarbeiten" ts="2507212300" ts-tts="25-07-27 23:16:04.177" pr="2"/>
		

	</s>
	



	<s id="-8507579369629779252-2507280838-11" eva="8003446">
		
    
		<m id="r2197542" t="h" from="2507150000" to="2508041000" cat="Bauarbeiten" ts="2507212300" ts-tts="25-07-27 23:16:04.177" pr="2"/>
		
    
		<ar l="14">
			
        
			<m id="r21640063" t="f" c="0" ts="2507261617" ts-tts="25-07-26 16:17:16.486"/>
			
        
			<m id="r21658971" t="f" c="0" ts="2507270139" ts-tts="25-07-27 01:39:31.066"/>
			
    
		</ar>
		
    
		<dp l="14">
			
        
			<m id="r21640063" t="f" c="0" ts="2507261617" ts-tts="25-07-26 16:17:16.486"/>
			
        
			<m id="r21658971" t="f" c="0" ts="2507270139" ts-tts="25-07-27 01:39:31.066"/>
			
    
		</dp>
		

	</s>
	



	<s id="7308971991516048789-2507280628-15" eva="8003446">
		
    
		<m id="r2197542" t="h" from="2507150000" to="2508041000" cat="Bauarbeiten" ts="2507212300" ts-tts="25-07-27 23:16:04.177" pr="2"/>
		

	</s>
	



	<s id="6738858581739970611-2507272147-12" eva="8003446">
		
    
		<ar ct="2507272246" l="14"/>
		
    
		<dp ct="2507272247" l="14"/>
		

	</s>
	



	<s id="9111999396693229187-2507272038-19" eva="8003446">
		
    
		<m id="r2197542" t="h" from="2507150000" to="2508041000" cat="Bauarbeiten" ts="2507212300" ts-tts="25-07-26 23:16:03.951" pr="2"/>
		
    
		<ar ct="2507272223" l="14"/>
		
    
		<dp ct="2507272224" l="14"/>
		

	</s>
	



	<s id="5429242306657575719-2507272047-12" eva="8003446">
		
    
		<ar ct="2507272146" l="14"/>
		
    
		<dp ct="2507272147" l="14"/>
		

	</s>
	



	<s id="-5387412643336057008-2507271938-17" eva="8003446">
		
    
		<m id="r2465528" t="h" from="2507271338" to="2507272207" cat="Information" ts="2507271425" ts-tts="25-07-27 14:26:01.152" pr="1"/>
		
    
		<m id="r2197542" t="h" from="2507150000" to="2508041000" cat="Bauarbeiten" ts="2507212300" ts-tts="25-07-26 23:16:03.951" pr="2"/>
		
    
		<ar ct="2507272105" l="14"/>
		
    
		<dp ct="2507272107" l="14"/>
		

	</s>
	



	<s id="315186145003258570-2507271947-12" eva="8003446">
		
    
		<ar ct="2507272045" l="14"/>
		
    
		<dp ct="2507272047" l="14"/>
		

	</s>
	



	<s id="-6041317011031353671-2507271749-9" eva="8003446">
		
    
		<ar ct="2507272024"/>
		
    
		<dp ct="2507272026"/>
		

	</s>
	



	<s id="-1528889229363705470-2507271838-11" eva="8003446">
		
    
		<m id="r2197542" t="h" from="2507150000" to="2508041000" cat="Bauarbeiten" ts="2507212300" ts-tts="25-07-26 23:16:03.951" pr="2"/>
		
    
		<ar ct="2507272002" l="14"/>
		
    
		<dp ct="2507272003" l="14"/>
		

	</s>
	



	<s id="5238745323128287854-2507271900-10" eva="8003446">
		
    
		<ar ct="2507271955" l="14"/>
		
    
		<dp ct="2507271956" l="14"/>
		

	</s>
	



	<s id="763582662722656356-2507271904-14" eva="8003446">
		
    
		<ar ct="2507271951" l="25"/>
		

	</s>
	



	<s id="1579706340622186127-2507271905-1" eva="8003446">
		
    
		<dp ct="2507271905" l="25"/>
		

	</s>
	



	<s id="-2421490829061645293-2507271740-13" eva="8003446">
		
    
		<m id="r2197542" t="h" from="2507150000" to="2508041000" cat="Bauarbeiten" ts="2507212300" ts-tts="25-07-26 23:16:03.951" pr="2"/>
		
    
		<ar ct="2507271901" l="14"/>
		
    
		<dp ct="2507271903" l="14"/>
		

	</s>
	



	<s id="-3434489727963259537-2507271755-12" eva="8003446">
		
    
		<ar ct="2507271858" l="14"/>
		
    
		<dp ct="2507271858" l="14"/>
		

	</s>
	



	<s id="-8884985048752411729-2507271758-14" eva="8003446">
		
    
		<ar ct="2507271851" l="25">
			
        
			<m id="r21684516" t="d" c="43" ts="2507271808" ts-tts="25-07-27 18:08:19.846"/>
			
    
		</ar>
		

	</s>
	



	<s id="2900502764812082147-2507271638-12" eva="8003446">
		
    
		<m id="r2197542" t="h" from="2507150000" to="2508041000" cat="Bauarbeiten" ts="2507212300" ts-tts="25-07-26 23:16:03.951" pr="2"/>
		
    
		<ar ct="2507271806" l="14">
			
        
			<m id="r21683578" t="d" c="45" ts="2507271745" ts-tts="25-07-27 17:45:26.896"/>
			
    
		</ar>
		
    
		<dp ct="2507271807" l="14">
			
        
			<m id="r21683578" t="d" c="45" ts="2507271745" ts-tts="25-07-27 17:45:26.896"/>
			
    
		</dp>
		

	</s>
	



	<s id="1617509895391586853-2507271805-1" eva="8003446">
		
    
		<dp ct="2507271805" l="25"/>
		

	</s>
	



	<s id="5532038320047824464-2507271305-14" eva="8003446">
		
    
		<m id="r2444956" t="h" from="2506240000" to="2507302359" cat="Information" ts="2506241537" ts-tts="25-07-26 23:16:04.188" pr="2"/>
		
    
		<ar ppth="Karlsruhe Hbf|Pforzheim Hbf|Mühlacker|Stuttgart Hbf|Schwäbisch Gmünd|Aalen Hbf|Ellwangen|Crailsheim|Ansbach|Nürnberg Hbf|Erlangen|Bamberg|Lichtenfels" pp="2" ct="2507271802" pt="2507271730">
			
        
			<m id="r21672470" t="d" c="61" ts="2507271323" ts-tts="25-07-27 13:23:59.153"/>
			
        
			<m id="r21677557" t="f" c="0" ts="2507271541" ts-tts="25-07-27 15:41:27.063"/>
			
    
		</ar>
		
    
		<dp ppth="Ludwigsstadt|Saalfeld(Saale)|Rudolstadt(Thür)|Jena-Göschwitz|Jena Paradies|Naumburg(Saale)Hbf|Weißenfels|Leipzig Hbf" pp="2" ct="2507271803" pt="2507271731">
			
        
			<m id="r21672470" t="d" c="61" ts="2507271323" ts-tts="25-07-27 13:23:59.153"/>
			
        
			<m id="r21677557" t="f" c="0" ts="2507271541" ts-tts="25-07-27 15:41:27.063"/>
			
    
		</dp>
		
    
		<tl f="F" t="p" o="80" c="IC" n="2161"/>
		

	</s>
	



	<s id="-3730544567799673916-2507271704-14" eva="8003446">
		
    
		<ar ct="2507271759" l="25"/>
		

	</s>
	



	<s id="6856417002719173777-2507271700-10" eva="8003446">
		
    
		<m id="r2465528" t="h" from="2507271338" to="2507272207" cat="Information" ts="2507271425" ts-tts="25-07-27 14:26:01.152" pr="1"/>
		
    
		<ar ct="2507271756" l="14"/>
		
    
		<dp ct="2507271757" l="14"/>
		

	</s>
	



	<s id="-6459206617103634837-2507271538-13" eva="8003446">
		
    
		<m id="r2197542" t="h" from="2507150000" to="2508041000" cat="Bauarbeiten" ts="2507212300" ts-tts="25-07-26 23:16:03.951" pr="2"/>
		
    
		<ar ct="2507271717" l="14">
			
        
			<m id="r21677567" t="d" c="2" ts="2507271541" ts-tts="25-07-27 15:41:58.669"/>
			
    
		</ar>
		
    
		<dp ct="2507271717" l="14">
			
        
			<m id="r21677567" t="d" c="2" ts="2507271541" ts-tts="25-07-27 15:41:58.669"/>
			
    
		</dp>
		

	</s>
	



	<s id="-1459462870208821828-2507280958-14" eva="8003446">
		
    
		<ar l="25">
			
        
			<m id="r21640098" t="f" c="0" ts="2507261617" ts-tts="25-07-26 16:18:04.087"/>
			
        
			<m id="r21658973" t="f" c="0" ts="2507270139" ts-tts="25-07-27 01:39:31.060"/>
			
    
		</ar>
		

	</s>
	



	<s id="-8410482026363875473-2507271706-1" eva="8003446">
		
    
		<dp ct="2507271706" l="25"/>
		

	</s>
	



	<s id="-6838664558476264438-2507271555-12" eva="8003446">
		
    
		<ar ct="2507271653" l="14"/>
		
    
		<dp ct="2507271655" l="14"/>
		

	</s>
	



	<s id="8358588628583003087-2507271558-14" eva="8003446">
		
    
		<ar ct="2507271651" l="25"/>
		

	</s>
	



	<s id="3675320541711482357-2507271505-15" eva="8003446">
		
    
		<m id="r2444956" t="h" from="2506240000" to="2507302359" cat="Information" ts="2506241537" ts-tts="25-07-26 23:16:04.188" pr="2"/>
		
    
		<ar cpth="Karlsruhe Hbf|Pforzheim Hbf|Mühlacker|Vaihingen(Enz)|Stuttgart Hbf|Schwäbisch Gmünd|Aalen Hbf|Ellwangen|Crailsheim|Ansbach|Nürnberg Hbf" ct="2507271929" cs="c" clt="2507271628">
			
        
			<m id="r21674588" t="f" c="0" ts="2507271424" ts-tts="25-07-27 14:24:27.054"/>
			
        
			<m id="r21677078" t="d" c="61" ts="2507271529" ts-tts="25-07-27 15:30:07.262"/>
			
        
			<m id="r21679419" t="d" c="55" ts="2507271628" ts-tts="25-07-27 16:28:19.816"/>
			
        
			<m id="r21680678" t="d" c="38" ts="2507271647" ts-tts="25-07-27 16:47:52.971"/>
			
        
			<m id="r21680940" t="f" c="0" ts="2507271649" ts-tts="25-07-27 16:49:28.626"/>
			
    
		</ar>
		
    
		<dp cpth="" ct="2507271931" cs="c" clt="2507271628">
			
        
			<m id="r21674588" t="f" c="0" ts="2507271424" ts-tts="25-07-27 14:24:27.054"/>
			
        
			<m id="r21677078" t="d" c="61" ts="2507271529" ts-tts="25-07-27 15:30:07.262"/>
			
        
			<m id="r21679419" t="d" c="55" ts="2507271628" ts-tts="25-07-27 16:28:19.816"/>
			
        
			<m id="r21680678" t="d" c="38" ts="2507271647" ts-tts="25-07-27 16:47:52.971"/>
			
        
			<m id="r21680940" t="f" c="0" ts="2507271649" ts-tts="25-07-27 16:49:28.626"/>
			
    
		</dp>
		

	</s>
	



	<s id="2044823728383562621-2507271549-9" eva="8003446">
		
    
		<m id="r2444956" t="h" from="2506240000" to="2507302359" cat="Information" ts="2506241537" ts-tts="25-07-26 23:16:04.188" pr="2"/>
		
    
		<ar cpth="" ct="2507271829" cs="c" clt="2507271621">
			
        
			<m id="r21678368" t="d" c="36" ts="2507271602" ts-tts="25-07-27 16:02:28.726"/>
			
        
			<m id="r21678900" t="f" c="0" ts="2507271617" ts-tts="25-07-27 16:17:16.006"/>
			
        
			<m id="r21679194" t="d" c="36" ts="2507271621" ts-tts="25-07-27 16:21:45.428"/>
			
        
			<m id="r21679320" t="d" c="36" ts="2507271625" ts-tts="25-07-27 16:25:10.798"/>
			
        
			<m id="r21679406" t="d" c="55" ts="2507271627" ts-tts="25-07-27 16:28:03.956"/>
			
        
			<m id="r21679571" t="d" c="55" ts="2507271630" ts-tts="25-07-27 16:30:25.915"/>
			
    
		</ar>
		
    
		<dp cpth="" ct="2507271829" cs="c" clt="2507271621">
			
        
			<m id="r21678368" t="d" c="36" ts="2507271602" ts-tts="25-07-27 16:02:28.726"/>
			
        
			<m id="r21678900" t="f" c="0" ts="2507271617" ts-tts="25-07-27 16:17:16.006"/>
			
        
			<m id="r21679194" t="d" c="36" ts="2507271621" ts-tts="25-07-27 16:21:45.428"/>
			
        
			<m id="r21679320" t="d" c="36" ts="2507271625" ts-tts="25-07-27 16:25:10.798"/>
			
        
			<m id="r21679406" t="d" c="55" ts="2507271627" ts-tts="25-07-27 16:28:03.956"/>
			
        
			<m id="r21679571" t="d" c="55" ts="2507271630" ts-tts="25-07-27 16:30:25.915"/>
			
    
		</dp>
		

	</s>
	



	<s id="-3892470588894151283-2507271349-9" eva="8003446">
		
    
		<m id="r2465293" t="h" from="2507270637" to="2507272130" cat="Information" ts="2507270024" ts-tts="25-07-27 00:25:05.270" pr="2"/>
		
    
		<m id="r2444956" t="h" from="2506240000" to="2507302359" cat="Information" ts="2506241537" ts-tts="25-07-26 23:16:04.188" pr="2"/>
		
    
		<ar ct="2507271624">
			
        
			<m id="r21660692" t="q" c="93" ts="2507270420" ts-tts="25-07-27 04:20:56.309"/>
			
        
			<m id="r21675315" t="f" c="0" ts="2507271446" ts-tts="25-07-27 14:46:30.005"/>
			
    
		</ar>
		
    
		<dp ct="2507271626">
			
        
			<m id="r21660692" t="q" c="93" ts="2507270420" ts-tts="25-07-27 04:20:56.309"/>
			
        
			<m id="r21675315" t="f" c="0" ts="2507271446" ts-tts="25-07-27 14:46:30.005"/>
			
    
		</dp>
		

	</s>
	



	<s id="7731436915795807304-2507271605-1" eva="8003446">
		
    
		<dp cp="1" ct="2507271609" l="25"/>
		

	</s>
	



	<s id="1478557104463101738-2507271440-11" eva="8003446">
		
    
		<m id="r2197542" t="h" from="2507150000" to="2508041000" cat="Bauarbeiten" ts="2507212300" ts-tts="25-07-26 23:16:03.951" pr="2"/>
		
    
		<ar ct="2507271602" l="14">
			
        
			<m id="r21675648" t="d" c="43" ts="2507271456" ts-tts="25-07-27 14:56:13.075"/>
			
    
		</ar>
		
    
		<dp ct="2507271603" l="14">
			
        
			<m id="r21675648" t="d" c="43" ts="2507271456" ts-tts="25-07-27 14:56:13.075"/>
			
    
		</dp>
		

	</s>
	



	<s id="6566295007289634224-2507271500-10" eva="8003446">
		
    
		<ar ct="2507271556" l="14"/>
		
    
		<dp ct="2507271557" l="14"/>
		

	</s>
	



	<s id="-99221802425356281-2507271505-1" eva="8003446">
		
    
		<dp ct="2507271505" l="25"/>
		

	</s>
	



	<s id="2975085315850444113-2507271338-13" eva="8003446">
		
    
		<m id="r2465528" t="h" from="2507271338" to="2507272207" cat="Information" ts="2507271425" ts-tts="25-07-27 14:26:01.152" pr="1"/>
		
    
		<m id="r2197542" t="h" from="2507150000" to="2508041000" cat="Bauarbeiten" ts="2507212300" ts-tts="25-07-26 23:16:03.951" pr="2"/>
		
    
		<ar ct="2507271505" l="14">
			
        
			<m id="r21651383" t="f" c="0" ts="2507262042" ts-tts="25-07-26 20:42:37.223"/>
			
        
			<m id="r21651389" t="f" c="0" ts="2507262042" ts-tts="25-07-26 20:42:52.992"/>
			
        
			<m id="r21673129" t="d" c="43" ts="2507271342" ts-tts="25-07-27 13:42:07.273"/>
			
        
			<m id="r21674600" t="f" c="0" ts="2507271424" ts-tts="25-07-27 14:24:58.395"/>
			
    
		</ar>
		
    
		<dp ct="2507271505" l="14">
			
        
			<m id="r21651383" t="f" c="0" ts="2507262042" ts-tts="25-07-26 20:42:37.223"/>
			
        
			<m id="r21651389" t="f" c="0" ts="2507262042" ts-tts="25-07-26 20:42:52.992"/>
			
        
			<m id="r21673129" t="d" c="43" ts="2507271342" ts-tts="25-07-27 13:42:07.273"/>
			
        
			<m id="r21674600" t="f" c="0" ts="2507271424" ts-tts="25-07-27 14:24:58.395"/>
			
    
		</dp>
		

	</s>
	



	<s id="7079184473771990335-2507271355-12" eva="8003446">
		
    
		<ar ct="2507271455" l="14"/>
		
    
		<dp ct="2507271456" l="14"/>
		

	</s>
	



	<s id="-113756971786229411-2507270905-14" eva="8003446">
		
    
		<m id="r2444956" t="h" from="2506240000" to="2507302359" cat="Information" ts="2506241537" ts-tts="25-07-26 23:16:04.188" pr="2"/>
		
    
		<ar ct="2507271342">
			
        
			<m id="r21666488" t="d" c="38" ts="2507271024" ts-tts="25-07-27 10:24:16.970"/>
			
        
			<m id="r21667248" t="f" c="0" ts="2507271047" ts-tts="25-07-27 10:47:21.017"/>
			
    
		</ar>
		
    
		<dp ct="2507271342">
			
        
			<m id="r21666488" t="d" c="38" ts="2507271024" ts-tts="25-07-27 10:24:16.971"/>
			
        
			<m id="r21667248" t="f" c="0" ts="2507271047" ts-tts="25-07-27 10:47:21.017"/>
			
    
		</dp>
		

	</s>
	



	<s id="3302578414229695927-2507270949-9" eva="8003446">
		
    
		<m id="r2444956" t="h" from="2506240000" to="2507302359" cat="Information" ts="2506241537" ts-tts="25-07-26 23:16:04.188" pr="2"/>
		
    
		<ar ct="2507271224">
			
        
			<m id="r21665658" t="f" c="0" ts="2507270950" ts-tts="25-07-27 09:51:04.772"/>
			
        
			<m id="r21666518" t="f" c="0" ts="2507271025" ts-tts="25-07-27 10:25:19.766"/>
			
        
			<m id="r21667663" t="f" c="0" ts="2507271059" ts-tts="25-07-27 10:59:53.873"/>
			
    
		</ar>
		
    
		<dp ct="2507271226">
			
        
			<m id="r21665658" t="f" c="0" ts="2507270950" ts-tts="25-07-27 09:51:04.772"/>
			
        
			<m id="r21666518" t="f" c="0" ts="2507271025" ts-tts="25-07-27 10:25:19.766"/>
			
        
			<m id="r21667663" t="f" c="0" ts="2507271059" ts-tts="25-07-27 10:59:53.873"/>
			
    
		</dp>
		

	</s>
	


</timetable>
