<?xml version="1.0" ?>
<timetable station="Weilheim(Oberbay)" eva="8000220">
	


	<s id="5562576247892574783-2506052316-1" eva="8000220">
		
    
		<dp ct="2506052316" l="RB67"/>
		

	</s>
	



	<s id="-1151057268452720658-2506061311-19" eva="8000220">
		
    
		<m id="r2397178" t="h" from="2504021133" to="2506192359" cat="Information" ts="2504021134" ts-tts="25-06-05 23:16:05.009" pr="3"/>
		
    
		<m id="r2397244" t="h" from="2504021351" to="2507012359" cat="Information" ts="2504021355" ts-tts="25-06-05 23:16:05.009" pr="2"/>
		

	</s>
	



	<s id="-4209398305073301857-2506061332-4" eva="8000220">
		
    
		<m id="r2355957" t="h" from="2501241332" to="2512121823" cat="Information" ts="2501241342" ts-tts="25-06-05 23:16:04.985" pr="1"/>
		
    
		<ar l="6">
			
        
			<m id="r18643952" t="f" c="0" ts="2506021309" ts-tts="25-06-02 13:09:44.702"/>
			
        
			<m id="r18643953" t="f" c="1000" ts="2506021309" ts-tts="25-06-02 13:09:44.702"/>
			
        
			<m id="r18674225" t="f" c="0" ts="2506030138" ts-tts="25-06-03 01:38:16.414"/>
			
        
			<m id="r18674226" t="f" c="1000" ts="2506030138" ts-tts="25-06-03 01:38:16.414"/>
			
        
			<m id="r18730354" t="f" c="0" ts="2506040138" ts-tts="25-06-04 01:38:03.377"/>
			
        
			<m id="r18730355" t="f" c="1000" ts="2506040138" ts-tts="25-06-04 01:38:03.377"/>
			
        
			<m id="r18792386" t="f" c="0" ts="2506050135" ts-tts="25-06-05 01:36:00.312"/>
			
        
			<m id="r18792387" t="f" c="1000" ts="2506050135" ts-tts="25-06-05 01:36:00.312"/>
			
    
		</ar>
		
    
		<dp l="6">
			
        
			<m id="r18643952" t="f" c="0" ts="2506021309" ts-tts="25-06-02 13:09:44.702"/>
			
        
			<m id="r18643953" t="f" c="1000" ts="2506021309" ts-tts="25-06-02 13:09:44.702"/>
			
        
			<m id="r18674225" t="f" c="0" ts="2506030138" ts-tts="25-06-03 01:38:16.414"/>
			
        
			<m id="r18674226" t="f" c="1000" ts="2506030138" ts-tts="25-06-03 01:38:16.414"/>
			
        
			<m id="r18730354" t="f" c="0" ts="2506040138" ts-tts="25-06-04 01:38:03.377"/>
			
        
			<m id="r18730355" t="f" c="1000" ts="2506040138" ts-tts="25-06-04 01:38:03.377"/>
			
        
			<m id="r18792386" t="f" c="0" ts="2506050135" ts-tts="25-06-05 01:36:00.312"/>
			
        
			<m id="r18792387" t="f" c="1000" ts="2506050135" ts-tts="25-06-05 01:36:00.312"/>
			
    
		</dp>
		

	</s>
	



	<s id="9098958648393372126-2506061530-4" eva="8000220">
		
    
		<ar l="6">
			
        
			<m id="r18845657" t="f" c="0" ts="2506052117" ts-tts="25-06-05 21:17:47.109"/>
			
    
		</ar>
		
    
		<dp l="6">
			
        
			<m id="r18845657" t="f" c="0" ts="2506052117" ts-tts="25-06-05 21:17:47.109"/>
			
    
		</dp>
		

	</s>
	



	<s id="-1132115514607203488-2506052315-1" eva="8000220">
		
    
		<dp ct="2506052315" l="RB67"/>
		

	</s>
	



	<s id="-2888876816368760754-2506052307-9" eva="8000220">
		
    
		<ar ct="2506052347" l="6"/>
		
    
		<dp ct="2506052349" l="6"/>
		

	</s>
	



	<s id="3395043356052930420-2506052232-4" eva="8000220">
		
    
		<ar ct="2506052311" l="6"/>
		
    
		<dp ct="2506052312" l="6"/>
		

	</s>
	



	<s id="6452230539092544912-2506052332-4" eva="8000220">
		
    
		<ar ct="2506060010" l="6"/>
		
    
		<dp ct="2506060012" l="6"/>
		

	</s>
	



	<s id="-5585726597242187485-2506052207-9" eva="8000220">
		
    
		<ar ct="2506052247" l="6"/>
		
    
		<dp ct="2506052249" l="6"/>
		

	</s>
	



	<s id="7109667618521189343-2506052204-7" eva="8000220">
		
    
		<ar ct="2506052244" l="RB67"/>
		

	</s>
	



	<s id="-226114949741556372-2506052114-20" eva="8000220">
		
    
		<ar ct="2506052241" l="RB67"/>
		

	</s>
	



	<s id="1166503817758015915-2506052216-1" eva="8000220">
		
    
		<dp ct="2506052217" l="RB67">
			
        
			<m id="r18847337" t="f" c="0" ts="2506052206" ts-tts="25-06-05 22:06:28.593"/>
			
    
		</dp>
		

	</s>
	



	<s id="-4021240020148242656-2506052215-1" eva="8000220">
		
    
		<dp ct="2506052215" l="RB67">
			
        
			<m id="r18847336" t="f" c="0" ts="2506052206" ts-tts="25-06-05 22:06:28.593"/>
			
    
		</dp>
		

	</s>
	



	<s id="3838664418033096107-2506052132-4" eva="8000220">
		
    
		<m id="r754867530" t="c" ts="2506052206" ts-tts="25-06-05 22:06:28.524"/>
		
    
		<m id="r754867531" t="c" ts="2506052206" ts-tts="25-06-05 22:06:28.524"/>
		
    
		<ar cp="1" ct="2506052212" l="6"/>
		
    
		<dp cp="1" ct="2506052214" l="6"/>
		

	</s>
	



	<s id="-9029018834559513703-2506052107-9" eva="8000220">
		
    
		<ar ct="2506052148" l="6"/>
		
    
		<dp ct="2506052149" l="6"/>
		

	</s>
	



	<s id="56515565337882759-2506052104-7" eva="8000220">
		
    
		<ar ct="2506052145" l="RB67">
			
        
			<m id="r18846702" t="d" c="43" ts="2506052145" ts-tts="25-06-05 21:45:43.303"/>
			
    
		</ar>
		

	</s>
	



	<s id="1044451543661955798-2506052059-5" eva="8000220">
		
    
		<m id="r2423549" t="h" from="2506030100" to="2506060200" cat="Bauarbeiten" ts="2506022303" ts-tts="25-06-04 23:16:04.879" pr="2"/>
		
    
		<ar cp="3" ct="2506052144" l="65"/>
		

	</s>
	



	<s id="-3748617538204790006-2506052012-20" eva="8000220">
		
    
		<ar ct="2506052140" l="RB67"/>
		

	</s>
	



	<s id="7903524428631160305-2506060458-9" eva="8000220">
		
    
		<ar l="6">
			
        
			<m id="r18845671" t="f" c="0" ts="2506052117" ts-tts="25-06-05 21:18:03.012"/>
			
    
		</ar>
		
    
		<dp l="6">
			
        
			<m id="r18845671" t="f" c="0" ts="2506052117" ts-tts="25-06-05 21:18:03.012"/>
			
    
		</dp>
		

	</s>
	



	<s id="-1708689396206783496-2506052116-1" eva="8000220">
		
    
		<dp ct="2506052116" l="RB67"/>
		

	</s>
	



	<s id="5639078379620631349-2506052115-1" eva="8000220">
		
    
		<dp ct="2506052115" l="RB67"/>
		

	</s>
	



	<s id="-6638217267151571360-2506052032-4" eva="8000220">
		
    
		<ar ct="2506052111" l="6"/>
		
    
		<dp ct="2506052112" l="6"/>
		

	</s>
	



	<s id="6759763039452685538-2506052005-9" eva="8000220">
		
    
		<ar ct="2506052049" l="6"/>
		
    
		<dp ct="2506052050" l="6"/>
		

	</s>
	



	<s id="2495136835039162933-2506052004-7" eva="8000220">
		
    
		<ar ct="2506052045" l="RB67"/>
		

	</s>
	



	<s id="-5110577504596967873-2506051959-5" eva="8000220">
		
    
		<m id="r2423549" t="h" from="2506030100" to="2506060200" cat="Bauarbeiten" ts="2506022303" ts-tts="25-06-04 23:16:04.879" pr="2"/>
		
    
		<ar ct="2506052043" l="65"/>
		

	</s>
	



	<s id="-439162720865642768-2506051909-20" eva="8000220">
		
    
		<ar ct="2506052042" l="RB67"/>
		

	</s>
	



	<s id="1380826623650898738-2506060019-1" eva="8000220">
		
    
		<dp ct="2506060019" l="RB67"/>
		

	</s>
	



	<s id="6597443741402581740-2506051936-9" eva="8000220">
		
    
		<ar ct="2506052012" l="RB67">
			
        
			<m id="r18842260" t="d" c="43" ts="2506052001" ts-tts="25-06-05 20:01:31.885"/>
			
        
			<m id="r18842406" t="f" c="0" ts="2506052005" ts-tts="25-06-05 20:05:15.297"/>
			
        
			<m id="r18842996" t="f" c="0" ts="2506052016" ts-tts="25-06-05 20:17:13.265"/>
			
    
		</ar>
		
    
		<dp ct="2506052016" l="RB67">
			
        
			<m id="r18842260" t="d" c="43" ts="2506052001" ts-tts="25-06-05 20:01:31.885"/>
			
        
			<m id="r18842406" t="f" c="0" ts="2506052005" ts-tts="25-06-05 20:05:15.297"/>
			
        
			<m id="r18842996" t="f" c="0" ts="2506052016" ts-tts="25-06-05 20:17:13.265"/>
			
    
		</dp>
		

	</s>
	



	<s id="7673836740048407372-2506052002-2" eva="8000220">
		
    
		<ar ct="2506052013" l="RB67">
			
        
			<m id="r18842407" t="f" c="0" ts="2506052005" ts-tts="25-06-05 20:05:15.307"/>
			
    
		</ar>
		
    
		<dp ct="2506052016" l="RB67">
			
        
			<m id="r18842407" t="f" c="0" ts="2506052005" ts-tts="25-06-05 20:05:15.307"/>
			
    
		</dp>
		

	</s>
	



	<s id="4876128075804953288-2506052015-1" eva="8000220">
		
    
		<m id="r2423549" t="h" from="2506030100" to="2506060200" cat="Bauarbeiten" ts="2506022303" ts-tts="25-06-04 23:16:04.879" pr="2"/>
		
    
		<dp ct="2506052015" l="65"/>
		

	</s>
	



	<s id="3336562791046240759-2506051932-4" eva="8000220">
		
    
		<m id="r754866606" t="c" ts="2506052005" ts-tts="25-06-05 20:05:15.194"/>
		
    
		<m id="r754866607" t="c" ts="2506052005" ts-tts="25-06-05 20:05:15.194"/>
		
    
		<ar ct="2506052013" l="6">
			
        
			<m id="r18841959" t="d" c="43" ts="2506051954" ts-tts="25-06-05 19:54:21.244"/>
			
    
		</ar>
		
    
		<dp ct="2506052014" l="6">
			
        
			<m id="r18841959" t="d" c="43" ts="2506051954" ts-tts="25-06-05 19:54:21.244"/>
			
    
		</dp>
		

	</s>
	



	<s id="-7674699078596834624-2506051905-9" eva="8000220">
		
    
		<ar ct="2506051953" l="6">
			
        
			<m id="r18840855" t="d" c="44" ts="2506051929" ts-tts="25-06-05 19:29:31.710"/>
			
    
		</ar>
		
    
		<dp ct="2506051954" l="6">
			
        
			<m id="r18840855" t="d" c="44" ts="2506051929" ts-tts="25-06-05 19:29:31.710"/>
			
    
		</dp>
		

	</s>
	



	<s id="6637522297700359651-2506051904-7" eva="8000220">
		
    
		<ar ct="2506051944" l="RB67"/>
		
    
		<dp ct="2506051945" l="RB67"/>
		

	</s>
	



	<s id="-5176705013242239116-2506051812-20" eva="8000220">
		
    
		<ar ct="2506051943" l="RB67"/>
		
    
		<dp ct="2506051945" l="RB67"/>
		

	</s>
	



	<s id="-5976461233453508010-2506051856-5" eva="8000220">
		
    
		<ar ct="2506051939" l="6"/>
		
    
		<dp ct="2506051940" l="6"/>
		

	</s>
	



	<s id="2273009839802399952-2506051902-2" eva="8000220">
		
    
		<ar ct="2506051913" l="RB67">
			
        
			<m id="r18839633" t="f" c="0" ts="2506051904" ts-tts="25-06-05 19:04:54.612"/>
			
    
		</ar>
		
    
		<dp ct="2506051917" l="RB67">
			
        
			<m id="r18839633" t="f" c="0" ts="2506051904" ts-tts="25-06-05 19:04:54.612"/>
			
    
		</dp>
		

	</s>
	



	<s id="6313666815166482263-2506051836-9" eva="8000220">
		
    
		<ar ct="2506051914" l="RB67">
			
        
			<m id="r18839002" t="d" c="43" ts="2506051857" ts-tts="25-06-05 18:58:10.767"/>
			
        
			<m id="r18839631" t="f" c="0" ts="2506051904" ts-tts="25-06-05 19:04:54.611"/>
			
        
			<m id="r18840247" t="f" c="0" ts="2506051917" ts-tts="25-06-05 19:17:13.483"/>
			
    
		</ar>
		
    
		<dp ct="2506051916" l="RB67">
			
        
			<m id="r18839002" t="d" c="43" ts="2506051857" ts-tts="25-06-05 18:58:10.767"/>
			
        
			<m id="r18839631" t="f" c="0" ts="2506051904" ts-tts="25-06-05 19:04:54.611"/>
			
        
			<m id="r18840247" t="f" c="0" ts="2506051917" ts-tts="25-06-05 19:17:13.483"/>
			
    
		</dp>
		

	</s>
	



	<s id="3416774208358504040-2506061107-9" eva="8000220">
		
    
		<ar l="6">
			
        
			<m id="r18753473" t="f" c="0" ts="2506041205" ts-tts="25-06-04 12:05:56.580"/>
			
        
			<m id="r18792594" t="f" c="0" ts="2506050136" ts-tts="25-06-05 01:36:31.221"/>
			
    
		</ar>
		
    
		<dp l="6">
			
        
			<m id="r18753473" t="f" c="0" ts="2506041205" ts-tts="25-06-04 12:05:56.580"/>
			
        
			<m id="r18792594" t="f" c="0" ts="2506050136" ts-tts="25-06-05 01:36:31.221"/>
			
    
		</dp>
		

	</s>
	



	<s id="-7814730549342560413-2506051832-4" eva="8000220">
		
    
		<m id="r754865827" t="c" ts="2506051904" ts-tts="25-06-05 19:04:54.540"/>
		
    
		<m id="r754865826" t="c" ts="2506051904" ts-tts="25-06-05 19:04:54.540"/>
		
    
		<ar ct="2506051913" l="6">
			
        
			<m id="r18795305" t="q" c="85" ts="2506050425" ts-tts="25-06-05 04:25:29.025"/>
			
        
			<m id="r18838931" t="d" c="43" ts="2506051856" ts-tts="25-06-05 18:57:06.700"/>
			
    
		</ar>
		
    
		<dp ct="2506051915" l="6">
			
        
			<m id="r18795305" t="q" c="85" ts="2506050425" ts-tts="25-06-05 04:25:29.025"/>
			
        
			<m id="r18838931" t="d" c="43" ts="2506051856" ts-tts="25-06-05 18:57:06.700"/>
			
    
		</dp>
		

	</s>
	



	<s id="7283606230545512328-2506051912-1" eva="8000220">
		
    
		<m id="r2423549" t="h" from="2506030100" to="2506060200" cat="Bauarbeiten" ts="2506022303" ts-tts="25-06-04 23:16:04.879" pr="2"/>
		
    
		<dp ct="2506051914" l="65"/>
		

	</s>
	



	<s id="7595572746620507819-2506052304-7" eva="8000220">
		
    
		<ar ct="2506052344" l="RB67"/>
		

	</s>
	



	<s id="6210246247545649220-2506051805-9" eva="8000220">
		
    
		<ar ct="2506051854" l="6"/>
		
    
		<dp ct="2506051856" l="6"/>
		

	</s>
	



	<s id="-1565580237480600892-2506051813-3" eva="8000220">
		
    
		<ar ct="2506051851" l="61"/>
		
    
		<dp ct="2506051853" l="61"/>
		

	</s>
	



	<s id="4432853395779340536-2506051712-20" eva="8000220">
		
    
		<ar ct="2506051844" l="RB67">
			
        
			<m id="r18836956" t="d" c="43" ts="2506051823" ts-tts="25-06-05 18:24:03.213"/>
			
        
			<m id="r18838297" t="f" c="0" ts="2506051846" ts-tts="25-06-05 18:47:09.879"/>
			
    
		</ar>
		
    
		<dp ct="2506051846" l="RB67">
			
        
			<m id="r18836956" t="d" c="43" ts="2506051823" ts-tts="25-06-05 18:24:03.213"/>
			
        
			<m id="r18838297" t="f" c="0" ts="2506051846" ts-tts="25-06-05 18:47:09.879"/>
			
    
		</dp>
		

	</s>
	



	<s id="5080032595018259952-2506051804-7" eva="8000220">
		
    
		<ar ct="2506051844" l="RB67"/>
		
    
		<dp ct="2506051845" l="RB67"/>
		

	</s>
	



	<s id="4976704969139597363-2506051756-5" eva="8000220">
		
    
		<ar ct="2506051840" l="6"/>
		
    
		<dp ct="2506051842" l="6"/>
		

	</s>
	



	<s id="-394527209982887466-2506051816-1" eva="8000220">
		
    
		<dp ct="2506051818" l="RB67"/>
		

	</s>
	



	<s id="5516003221922456036-2506051802-2" eva="8000220">
		
    
		<ar ct="2506051813" l="RB67"/>
		
    
		<dp ct="2506051816" l="RB67"/>
		

	</s>
	



	<s id="1364730772586154623-2506051729-4" eva="8000220">
		
    
		<ar ct="2506051811" l="6"/>
		
    
		<dp ct="2506051815" l="6"/>
		

	</s>
	



	<s id="8576673980835508934-2506051737-9" eva="8000220">
		
    
		<ar ct="2506051815" l="RB67">
			
        
			<m id="r18836051" t="d" c="43" ts="2506051807" ts-tts="25-06-05 18:07:35.267"/>
			
    
		</ar>
		

	</s>
	



	<s id="3162957587933956298-2506052213-20" eva="8000220">
		
    
		<ar ct="2506052342" l="RB67"/>
		

	</s>
	



	<s id="10468269424094010-2506051812-1" eva="8000220">
		
    
		<m id="r2423549" t="h" from="2506030100" to="2506060200" cat="Bauarbeiten" ts="2506022303" ts-tts="25-06-04 23:16:04.879" pr="2"/>
		
    
		<dp ct="2506051812" l="65"/>
		

	</s>
	



	<s id="686597562313375896-2506051705-9" eva="8000220">
		
    
		<ar ct="2506051753" l="6"/>
		
    
		<dp ct="2506051754" l="6"/>
		

	</s>
	



	<s id="7379076267373173372-2506051713-3" eva="8000220">
		
    
		<ar ct="2506051751" l="61"/>
		
    
		<dp ct="2506051753" l="61"/>
		

	</s>
	



	<s id="3396411556503392031-2506051612-20" eva="8000220">
		
    
		<ar ct="2506051744" l="RB67">
			
        
			<m id="r18833240" t="d" c="99" ts="2506051723" ts-tts="25-06-05 17:23:12.688"/>
			
        
			<m id="r18834676" t="f" c="0" ts="2506051746" ts-tts="25-06-05 17:46:13.905"/>
			
    
		</ar>
		
    
		<dp ct="2506051745" l="RB67">
			
        
			<m id="r18833240" t="d" c="99" ts="2506051723" ts-tts="25-06-05 17:23:12.688"/>
			
        
			<m id="r18834676" t="f" c="0" ts="2506051746" ts-tts="25-06-05 17:46:13.905"/>
			
    
		</dp>
		

	</s>
	



	<s id="862464147585044720-2506051704-7" eva="8000220">
		
    
		<ar ct="2506051744" l="RB67"/>
		
    
		<dp ct="2506051745" l="RB67"/>
		

	</s>
	



	<s id="-957800096506590939-2506051657-5" eva="8000220">
		
    
		<ar ct="2506051739" l="6"/>
		
    
		<dp ct="2506051741" l="6"/>
		

	</s>
	



	<s id="7484485701898602624-2506051637-9" eva="8000220">
		
    
		<ar ct="2506051717" l="RB67">
			
        
			<m id="r18831185" t="d" c="43" ts="2506051652" ts-tts="25-06-05 16:52:54.435"/>
			
    
		</ar>
		
    
		<dp ct="2506051719" l="RB67">
			
        
			<m id="r18831185" t="d" c="43" ts="2506051652" ts-tts="25-06-05 16:52:54.435"/>
			
    
		</dp>
		

	</s>
	



	<s id="524047775000165779-2506051702-2" eva="8000220">
		
    
		<ar ct="2506051717" l="RB67">
			
        
			<m id="r18832740" t="d" c="48" ts="2506051716" ts-tts="25-06-05 17:16:26.102"/>
			
    
		</ar>
		
    
		<dp ct="2506051719" l="RB67">
			
        
			<m id="r18832740" t="d" c="48" ts="2506051716" ts-tts="25-06-05 17:16:26.102"/>
			
    
		</dp>
		

	</s>
	



	<s id="5111774224362867641-2506051715-1" eva="8000220">
		
    
		<m id="r2423549" t="h" from="2506030100" to="2506060200" cat="Bauarbeiten" ts="2506022303" ts-tts="25-06-04 23:16:04.879" pr="2"/>
		
    
		<m id="r2355960" t="h" from="2501241632" to="2512131800" cat="Information" ts="2501241347" ts-tts="25-06-04 23:16:04.652" pr="1"/>
		
    
		<dp ct="2506051716" l="65">
			
        
			<m id="r18644399" t="f" c="0" ts="2506021316" ts-tts="25-06-02 13:16:10.403"/>
			
        
			<m id="r18644400" t="f" c="1000" ts="2506021316" ts-tts="25-06-02 13:16:10.403"/>
			
        
			<m id="r18674235" t="f" c="0" ts="2506030138" ts-tts="25-06-03 01:38:16.413"/>
			
        
			<m id="r18674236" t="f" c="1000" ts="2506030138" ts-tts="25-06-03 01:38:16.413"/>
			
        
			<m id="r18730360" t="f" c="0" ts="2506040138" ts-tts="25-06-04 01:38:03.376"/>
			
        
			<m id="r18730361" t="f" c="1000" ts="2506040138" ts-tts="25-06-04 01:38:03.376"/>
			
    
		</dp>
		

	</s>
	



	<s id="7431345833869246893-2506051632-4" eva="8000220">
		
    
		<m id="r2355960" t="h" from="2501241632" to="2512131800" cat="Information" ts="2501241347" ts-tts="25-06-04 23:16:04.652" pr="1"/>
		
    
		<ar ct="2506051712" l="6">
			
        
			<m id="r18644045" t="f" c="0" ts="2506021311" ts-tts="25-06-02 13:11:38.464"/>
			
        
			<m id="r18644046" t="f" c="1000" ts="2506021311" ts-tts="25-06-02 13:11:38.464"/>
			
        
			<m id="r18674229" t="f" c="0" ts="2506030138" ts-tts="25-06-03 01:38:16.414"/>
			
        
			<m id="r18674230" t="f" c="1000" ts="2506030138" ts-tts="25-06-03 01:38:16.414"/>
			
        
			<m id="r18730358" t="f" c="0" ts="2506040138" ts-tts="25-06-04 01:38:03.377"/>
			
        
			<m id="r18730359" t="f" c="1000" ts="2506040138" ts-tts="25-06-04 01:38:03.377"/>
			
    
		</ar>
		
    
		<dp ct="2506051714" l="6">
			
        
			<m id="r18644045" t="f" c="0" ts="2506021311" ts-tts="25-06-02 13:11:38.464"/>
			
        
			<m id="r18644046" t="f" c="1000" ts="2506021311" ts-tts="25-06-02 13:11:38.464"/>
			
        
			<m id="r18674229" t="f" c="0" ts="2506030138" ts-tts="25-06-03 01:38:16.414"/>
			
        
			<m id="r18674230" t="f" c="1000" ts="2506030138" ts-tts="25-06-03 01:38:16.414"/>
			
        
			<m id="r18730358" t="f" c="0" ts="2506040138" ts-tts="25-06-04 01:38:03.377"/>
			
        
			<m id="r18730359" t="f" c="1000" ts="2506040138" ts-tts="25-06-04 01:38:03.377"/>
			
    
		</dp>
		

	</s>
	



	<s id="1636613662607894889-2506051610-3" eva="8000220">
		
    
		<ar ct="2506051655" l="61">
			
        
			<m id="r18828472" t="d" c="47" ts="2506051611" ts-tts="25-06-05 16:11:15.876"/>
			
    
		</ar>
		
    
		<dp ct="2506051656" l="61">
			
        
			<m id="r18828472" t="d" c="47" ts="2506051611" ts-tts="25-06-05 16:11:15.876"/>
			
    
		</dp>
		

	</s>
	



	<s id="4323289677795304033-2506051605-9" eva="8000220">
		
    
		<ar ct="2506051650" l="6">
			
        
			<m id="r18795303" t="q" c="85" ts="2506050425" ts-tts="25-06-05 04:25:13.562"/>
			
    
		</ar>
		
    
		<dp ct="2506051654" l="6">
			
        
			<m id="r18795303" t="q" c="85" ts="2506050425" ts-tts="25-06-05 04:25:13.562"/>
			
    
		</dp>
		

	</s>
	



	<s id="-4738574861795120641-2506051604-7" eva="8000220">
		
    
		<ar ct="2506051647" l="RB67">
			
        
			<m id="r18828650" t="d" c="48" ts="2506051613" ts-tts="25-06-05 16:14:14.320"/>
			
    
		</ar>
		
    
		<dp ct="2506051653" l="RB67">
			
        
			<m id="r18828650" t="d" c="48" ts="2506051613" ts-tts="25-06-05 16:14:14.320"/>
			
    
		</dp>
		

	</s>
	



	<s id="1382257194107462138-2506051457-24" eva="8000220">
		
    
		<ar ct="2506051648" l="RB67"/>
		
    
		<dp ct="2506051651" l="RB67"/>
		

	</s>
	



	<s id="989772101748846936-2506051556-5" eva="8000220">
		
    
		<ar ct="2506051640" l="6"/>
		
    
		<dp ct="2506051642" l="6"/>
		

	</s>
	



	<s id="5788718635749503289-2506051616-1" eva="8000220">
		
    
		<dp ct="2506051616" l="RB67"/>
		

	</s>
	



	<s id="-472807074205243028-2506051615-1" eva="8000220">
		
    
		<dp ct="2506051615" l="RB67"/>
		

	</s>
	



	<s id="7058493543944770687-2506060807-9" eva="8000220">
		
    
		<ar l="6">
			
        
			<m id="r18753311" t="f" c="0" ts="2506041202" ts-tts="25-06-04 12:02:43.528"/>
			
        
			<m id="r18792592" t="f" c="0" ts="2506050136" ts-tts="25-06-05 01:36:31.221"/>
			
    
		</ar>
		
    
		<dp l="6">
			
        
			<m id="r18753311" t="f" c="0" ts="2506041202" ts-tts="25-06-04 12:02:43.528"/>
			
        
			<m id="r18792592" t="f" c="0" ts="2506050136" ts-tts="25-06-05 01:36:31.221"/>
			
    
		</dp>
		

	</s>
	



	<s id="9098958648393372126-2506051530-4" eva="8000220">
		
    
		<ar ct="2506051611" l="6"/>
		
    
		<dp ct="2506051613" l="6"/>
		

	</s>
	



	<s id="-1992986826698818223-2506051612-1" eva="8000220">
		
    
		<m id="r2423549" t="h" from="2506030100" to="2506060200" cat="Bauarbeiten" ts="2506022303" ts-tts="25-06-04 23:16:04.879" pr="2"/>
		
    
		<dp ct="2506051612" l="65"/>
		

	</s>
	



	<s id="-1443977141737168954-2506051504-7" eva="8000220">
		
    
		<ar ct="2506051553" l="RB67">
			
        
			<m id="r18824487" t="d" c="48" ts="2506051502" ts-tts="25-06-05 15:03:12.591"/>
			
    
		</ar>
		
    
		<dp ct="2506051554" l="RB67">
			
        
			<m id="r18824487" t="d" c="48" ts="2506051502" ts-tts="25-06-05 15:03:12.591"/>
			
    
		</dp>
		

	</s>
	



	<s id="-3242978816071942777-2506051507-9" eva="8000220">
		
    
		<ar ct="2506051549" l="6"/>
		
    
		<dp ct="2506051550" l="6"/>
		

	</s>
	



	<s id="3510110135137636718-2506051516-1" eva="8000220">
		
    
		<dp ct="2506051526" l="RB67">
			
        
			<m id="r18825973" t="d" c="47" ts="2506051530" ts-tts="25-06-05 15:30:09.682"/>
			
    
		</dp>
		

	</s>
	



	<s id="-6176963926202499966-2506051515-1" eva="8000220">
		
    
		<dp ct="2506051527" l="RB67">
			
        
			<m id="r18825939" t="d" c="47" ts="2506051529" ts-tts="25-06-05 15:29:37.490"/>
			
    
		</dp>
		

	</s>
	



	<s id="3339188053375239505-2506051515-1" eva="8000220">
		
    
		<m id="r2423549" t="h" from="2506030100" to="2506060200" cat="Bauarbeiten" ts="2506022303" ts-tts="25-06-04 23:16:04.879" pr="2"/>
		
    
		<dp ct="2506051518" l="65"/>
		

	</s>
	



	<s id="8732183210536966340-2506052312-20" eva="8000220">
		
    
		<ar ct="2506060042" l="RB67"/>
		

	</s>
	


</timetable>
